{
  "version": 1,
  "skills": {
    "find-skills": {
      "source": "vercel-labs/skills",
      "sourceType": "github",
      "skillPath": "skills/find-skills/SKILL.md",
      "computedHash": "781bd6d3f9b19f8c9af6b53d8d0e4876d0183841b565db34ca7092ffa412d111"
    },
    "insforge": {
      "source": "insforge/agent-skills",
      "sourceType": "github",
      "skillPath": "skills/insforge/SKILL.md",
      "computedHash": "f044b969a4f6257adb51732e20d3cb395ed6627933caa89255af420717242ec8"
    },
    "insforge-cli": {
      "source": "insforge/agent-skills",
      "sourceType": "github",
      "skillPath": "skills/insforge-cli/SKILL.md",
      "computedHash": "aa3583893a7aff9242df7caf6d3d69d8194653959c49a7a00b927195a7249f09"
    },
    "insforge-debug": {
      "source": "insforge/agent-skills",
      "sourceType": "github",
      "skillPath": "skills/insforge-debug/SKILL.md",
      "computedHash": "cd683fd2010dbcb75f07d990098b41bc28d3dcd40f7289de1978dfff07b6f142"
    },
    "insforge-integrations": {
      "source": "insforge/agent-skills",
      "sourceType": "github",
      "skillPath": "skills/insforge-integrations/SKILL.md",
      "computedHash": "2029ae7db3384449b36a455e4f6c91ff1de0d38c17ff2c12a7bd41c5835abc78"
    }
  }
}
